rhutils/__init__.py
rhutils/rhutils.py
rhutils-0.1.0.dist-info/LICENSE
rhutils-0.1.0.dist-info/METADATA
rhutils-0.1.0.dist-info/WHEEL
rhutils-0.1.0.dist-info/top_level.txt
rhutils-0.1.0.dist-info/RECORD
