Metadata-Version: 2.1
Name: rhutils
Version: 0.1.0
Summary: Rhesus factor utilities
Home-page: https://github.com/allanbreyes/rhutils
Author: Allan Reyes
Author-email: pypi@reyes.sh
License: MIT license
Keywords: rhutils
Platform: UNKNOWN
Classifier: Development Status :: 2 - Pre-Alpha
Classifier: Intended Audience :: Developers
Classifier: License :: OSI Approved :: MIT License
Classifier: Natural Language :: English
Classifier: Programming Language :: Python :: 3
Classifier: Programming Language :: Python :: 3.5
Classifier: Programming Language :: Python :: 3.6
Classifier: Programming Language :: Python :: 3.7
Classifier: Programming Language :: Python :: 3.8
Requires-Python: >=3.5
